[{"i":"110000","n":"北京市","a":"北京","y":"BeiJing","b":"BJ","z":"100000"},{"i":"310000","n":"上海市","a":"上海","y":"ShangHai","b":"SH","z":"200000"},{"i":"320000","n":"江苏省","a":"江苏","y":"JiangSu","b":"JS","z":"210000"},{"i":"340000","n":"安徽省","a":"安徽","y":"AnHui","b":"AH","z":"230000"},{"i":"500000","n":"重庆市","a":"重庆","y":"ZhongQing","b":"ZQ","z":"400000"},{"i":"650000","n":"新疆维吾尔自治区","a":"新疆维吾尔","y":"XinJiangWeiWuEr","b":"XJWWE","z":"830000"},{"i":"710000","n":"台湾省","a":"台湾","y":"TaiWan","b":"TW","z":""},{"i":"810000","n":"香港特别行政区","a":"香港","y":"HongKong","b":"HK","z":""},{"i":"820000","n":"澳门特别行政区","a":"澳门","y":"Macau","b":"MAC","z":""}]